gundog_core/__init__.py
gundog_core/client.py
gundog_core/config.py
gundog_core/errors.py
gundog_core/types.py
gundog_core-0.4.1.dist-info/METADATA
gundog_core-0.4.1.dist-info/WHEEL
gundog_core-0.4.1.dist-info/RECORD
