Metadata-Version: 2.4
Name: gundog-core
Version: 0.4.1
Summary: Shared types, protocols, and client for gundog semantic search
Author: ivdi
License-Expression: GPL-3.0-or-later
Classifier: Development Status :: 3 - Alpha
Classifier: Intended Audience :: Developers
Classifier: License :: OSI Approved :: GNU General Public License v3 or later (GPLv3+)
Classifier: Programming Language :: Python :: 3
Classifier: Programming Language :: Python :: 3.12
Classifier: Programming Language :: Python :: 3.13
Requires-Python: >=3.12
Requires-Dist: httpx>=0.27.0
Requires-Dist: pyyaml>=6.0
Requires-Dist: websockets>=12.0
